README.md
setup.py
qdutils/__init__.py
qdutils.egg-info/PKG-INFO
qdutils.egg-info/SOURCES.txt
qdutils.egg-info/dependency_links.txt
qdutils.egg-info/top_level.txt
qdutils/common/__init__.py
qdutils/common/dateutils.py
qdutils/common/httputils.py
qdutils/common/stringutils.py
qdutils/common/timereplace.py
qdutils/database/__init__.py
qdutils/database/mysqlutils.py
qdutils/log/__init__.py
qdutils/log/logutils.py
qdutils/service/__init__.py
qdutils/service/sendding.py
qdutils/service/sendmail.py