Metadata-Version: 1.1
Name: qdutils
Version: 0.9
Summary: python common utils
Home-page: https://github.com/qdutils
Author: tony
Author-email: 874404359@qq.com
License: UNKNOWN
Platform: UNKNOWN
Classifier: Programming Language :: Python :: 2
Classifier: License :: OSI Approved :: MIT License
Classifier: Operating System :: OS Independent
